README.rst
setup.py
playlist/__init__.py
playlist/cli.py
playlist/playlist.py
playlistdb.egg-info/PKG-INFO
playlistdb.egg-info/SOURCES.txt
playlistdb.egg-info/dependency_links.txt
playlistdb.egg-info/entry_points.txt
playlistdb.egg-info/requires.txt
playlistdb.egg-info/top_level.txt